automatic_meter_reader/__init__.py
automatic_meter_reader/cameras/espcam_120_deg.json
automatic_meter_reader/meter_models/gas_bk25/meter_config.json
automatic_meter_reader/meter_models/gas_bk25/template_0.jpg
automatic_meter_reader/meter_models/gas_bk25/template_1.jpg
automatic_meter_reader/meter_models/gas_bk25/template_2.jpg
automatic_meter_reader/meter_models/lorenz_1997/meter_config.json
automatic_meter_reader/meter_models/lorenz_1997/template_0.jpg
automatic_meter_reader/meter_models/lorenz_1997/template_1.jpg
automatic_meter_reader/meter_models/lorenz_1997/template_2.jpg
automatic_meter_reader/meter_models/wehrle_cold/meter_config.json
automatic_meter_reader/meter_models/wehrle_cold/template_0.jpg
automatic_meter_reader/meter_models/wehrle_cold/template_1.jpg
automatic_meter_reader/meter_models/wehrle_cold/template_2.jpg
automatic_meter_reader/meter_models/wehrle_hot/meter_config.json
automatic_meter_reader/meter_models/wehrle_hot/template_0.jpg
automatic_meter_reader/meter_models/wehrle_hot/template_1.jpg
automatic_meter_reader/meter_models/wehrle_hot/template_2.jpg
automatic_meter_reader-0.1.10.dist-info/METADATA
automatic_meter_reader-0.1.10.dist-info/WHEEL
automatic_meter_reader-0.1.10.dist-info/top_level.txt
automatic_meter_reader-0.1.10.dist-info/RECORD
